LICENSE
README.md
setup.py
youtube_search_music/__init__.py
youtube_search_music.egg-info/PKG-INFO
youtube_search_music.egg-info/SOURCES.txt
youtube_search_music.egg-info/dependency_links.txt
youtube_search_music.egg-info/requires.txt
youtube_search_music.egg-info/top_level.txt