Metadata-Version: 2.1
Name: youtube-search-music
Version: 2.1.2
Summary: Perform YouTube music video searches using API
Home-page: https://github.com/DWAA1660/youtube_music_search
Author: DWAA1660
Author-email: dwatnip123@gmail.com
License: MIT
Platform: UNKNOWN
Classifier: License :: OSI Approved :: MIT License
Classifier: Programming Language :: Python :: 3
Classifier: Programming Language :: Python :: 3.7
Classifier: Programming Language :: Python :: 3.8
Classifier: Programming Language :: Python :: 3.10
License-File: LICENSE
